ticket_ynab_sync/__init__.py
ticket_ynab_sync/__main__.py
ticket_ynab_sync/cli.py
ticket_ynab_sync/models.py
ticket_ynab_sync/ticket_ynab_sync.py
ticket_ynab_sync/utils.py
ticket_ynab_sync/ynab.py
ticket_ynab_sync-0.0.1.dist-info/LICENSE
ticket_ynab_sync-0.0.1.dist-info/METADATA
ticket_ynab_sync-0.0.1.dist-info/WHEEL
ticket_ynab_sync-0.0.1.dist-info/entry_points.txt
ticket_ynab_sync-0.0.1.dist-info/top_level.txt
ticket_ynab_sync-0.0.1.dist-info/RECORD
