Metadata-Version: 2.1
Name: ticket-ynab-sync
Version: 0.0.1
Summary: Get transactions from ticket food card and sync them with a YNAB account.
Author-email: diogoaos <ticket_ynab_sync@diogoaos.com>
License: MIT License
Keywords: api,parser,transactions
Classifier: License :: OSI Approved :: MIT License
Classifier: Programming Language :: Python
Classifier: Programming Language :: Python :: 3
Requires-Python: >=3.7
License-File: LICENSE
Requires-Dist: click
Requires-Dist: ynab-api
Requires-Dist: pyticketfood
Provides-Extra: dev
Requires-Dist: black ; extra == 'dev'
Requires-Dist: bumpver ; extra == 'dev'
Requires-Dist: isort ; extra == 'dev'
Requires-Dist: pip-tools ; extra == 'dev'
Requires-Dist: pytest ; extra == 'dev'
